{
    "Wooden":
    [
        [
            {
                "loc":"32.85472495250175,-117.20607060378454",
                "heading":320
            },
            {
                "loc":"32.854837673126696,-117.20611263717443",
                "heading":310
            },
            {
                "loc":"32.85492594821493,-117.20614335388244",
                "heading":250
            },
            {
                "loc":"32.85500471668104,-117.2061918539477",
                "heading":200
            },
            {
                "loc":"32.85519495495472,-117.20626003117988",
                "heading": 180
                
            }
        ],
        [
            {
                "loc":"32.851499841092284,-117.19531264847686",
                "heading":250
            },
            {
                "loc":"32.851511107433424,-117.19542798345726",
                "heading":235
            },
            {
                "loc":"32.851522524598025,-117.19548426199944",
                "heading":170
            },
            {
                    "loc":"32.85152513766323,-117.19558141419681",
                "heading":130
            },
            {
                "loc":"32.851536404001166,-117.19569406696837",
                "heading": 120
                
            }
        ],
        [
            {   
                "loc":"32.85261110286101,-117.19874941237258",
                "heading":100
            },
            {
                "loc":"32.85249686564184,-117.19865808541608",
                "heading":85
            },
            {
                "loc":"32.85246081374565,-117.19857225473051",
                "heading":35
            },
            {
                "loc":"32.85241481657589,-117.19846627350306",
                "heading":335
            },
            {
                "loc":"32.852392284121635,-117.19841799374137",
                "heading": 320
                
            }
        ],
        [
            {
                "loc":"32.851313851036785,-117.19490002552418",
                "heading":180
            },
            {
                "loc":"32.851164555883216,-117.19492779349409",
                "heading":155
            },
            {
                "loc":"32.8511024917938,-117.19493877162263",
                "heading":70
            },
            {
                "loc":"32.85097506004374,-117.19496124411738",
                "heading":45
            },
            {
                "loc":"32.85089010544203,-117.1949556259937",
                "heading": 30
                
            }
        ],
        [
            {
                "loc":"32.851536404001166,-117.19569406696837",
                "heading":80
            },
            {
                "loc":"32.85152513766323,-117.19558141419681",
                "heading":70
            },
            {
                "loc":"32.851522524598025,-117.19548426199944",
                "heading":20
            },
            {
                "loc":"32.851511107433424,-117.19542798345726",
                "heading": 310
                
            },
            {
                "loc":"32.851499841092284,-117.19531264847686",
                "heading":295
            }
        ],
        [
            {"loc":"32.7951046,-117.2390604",
            "heading":60},
            {"loc":"32.7951289,-117.2389585",
            "heading":50},
            {"loc":"32.7951524,-117.2388552",
            "heading":0},
            {"loc":"32.7951765,-117.238749",
            "heading":282},
            {"loc":"32.7952002,-117.2386395",
            "heading":274}
        ],
        [
            {"loc":"32.8348936,-117.2074529",
            "heading":332},
            {"loc":"32.834982,-117.2074505",
            "heading":305},
            {"loc":"32.8350715,-117.2074497",
            "heading":248},
            {"loc":"32.8351641,-117.2074471",
            "heading":210},
            {"loc":"32.835259,-117.2074447",
            "heading":197}
        ],
        [
            {"loc":"32.8334597,-117.2101995",
            "heading":273},
            {"loc":"32.8334867,-117.2103043",
            "heading":247},
            {"loc":"32.8335238,-117.2104023",
            "heading":168},
            {"loc":"32.8335686,-117.2104889",
            "heading":147},
            {"loc":"32.8336226,-117.2106623",
            "heading":126}
        ]
    ],
    "Metal":
    [
        [
            {"loc": "32.6911841,-117.1839155",
            "heading": 104},
            {"loc":"32.6911392,-117.1838099",
            "heading": 95},
            {"loc":"32.6910581,-117.183741",
            "heading":31},
            {"loc":"32.6910253,-117.1836195",
            "heading":342},
            {"loc":"32.6909835,-117.183518",
            "heading":"324"}
        ],
        [
            {"loc":"32.8196346,-117.1861375",
            "heading":150},
            {"loc":"32.8195283,-117.1861259",
            "heading":138},
            {"loc":"32.8193957,-117.1861033",
            "heading":63},
            {"loc":"32.8193058,-117.1860826",
            "heading":38},
            {"loc":"32.8192115,-117.1860606",
            "heading":13}
        ],
        [
            {"loc":"32.8199737,-117.186151",
            "heading":1445},
            {"loc":"32.8198836,-117.1861489",
            "heading":120},
            {"loc":"32.8197936,-117.1861468",
            "heading":75},
            {"loc":"32.8197126,-117.1861426",
            "heading":40},
            {"loc":"32.8196346,-117.1861375",
            "heading":20}
        ],
        [
            {"loc":"32.8209644,-117.1861909",
            "heading":143},
            {"loc":"32.8209159,-117.1861404",
            "heading":150},
            {"loc":"32.8208604,-117.1861909",
            "heading":102},
            {"loc":"32.8207632,-117.1861873",
            "heading":55},
            {"loc":"32.8206631,-117.1861787",
            "heading":30}
        ],
        [
            {"loc":"32.8258436,-117.172705",
            "heading":85},
            {"loc":"32.8257946,-117.1726207",
            "heading":55},
            {"loc":"32.8257472,-117.1725383",
            "heading":16},
            {"loc":"32.825707,-117.1724528",
            "heading":338},
            {"loc":"32.8256569,-117.1723227",
            "heading":317}
        ],
        [
            {"loc":"32.7929852,-117.2357614",
            "heading":235},
            {"loc":"32.7929594,-117.2358722",
            "heading":203},
            {"loc":"32.7929439,-117.2359356",
            "heading":185},
            {"loc":"32.7929163,-117.2360361",
            "heading":117},
            {"loc":"32.792891,-117.2361805",
            "heading":100}
        ],
        [
            {"loc":"32.7935122,-117.2442216",
            "heading":240},
            {"loc":"32.7934877,-117.2443192",
            "heading":217},
            {"loc":"32.793464,-117.244423",
            "heading":118},
            {"loc":"32.7934371,-117.2445294",
            "heading":88},
            {"loc":"32.7934219,-117.2446227",
            "heading":85}
        ],
        [
            {"loc":"32.7942024,-117.241052",
            "heading":238},
            {"loc":"32.7941871,-117.2411203",
            "heading":229},
            {"loc":"32.7941628,-117.2412236",
            "heading":166},
            {"loc":"32.7941379,-117.2413348",
            "heading":113},
            {"loc":"32.7941154,-117.2414379",
            "heading":90}
        ]
    ]
}